kivy_garden/wordcloud/__init__.py
kivy_garden.wordcloud-1.0.0.dist-info/METADATA
kivy_garden.wordcloud-1.0.0.dist-info/RECORD
kivy_garden.wordcloud-1.0.0.dist-info/WHEEL
kivy_garden.wordcloud-1.0.0.dist-info/top_level.txt
