Metadata-Version: 2.1
Name: kivy-garden.wordcloud
Version: 1.0.0
Summary: A wordcloud widget for kivy.
Home-page: https://github.com/kivy-garden/wordcloud
Author: Kivy
Author-email: kivy@kivy.org
License: UNKNOWN
Project-URL: Bug Reports, https://github.com/kivy-garden/wordcloud/issues
Project-URL: Source, https://github.com/kivy-garden/wordcloud
Keywords: Kivy kivy-garden
Platform: UNKNOWN
Classifier: Development Status :: 4 - Beta
Classifier: Intended Audience :: Developers
Classifier: Topic :: Software Development :: Libraries
Classifier: License :: OSI Approved :: MIT License
Classifier: Programming Language :: Python :: 3.5
Classifier: Programming Language :: Python :: 3.6
Classifier: Programming Language :: Python :: 3.7
Provides-Extra: travis
Provides-Extra: dev
Provides-Extra: dev
Requires-Dist: pytest (>=3.6); extra == 'dev'
Requires-Dist: wheel; extra == 'dev'
Requires-Dist: pytest-cov; extra == 'dev'
Requires-Dist: pycodestyle; extra == 'dev'
Provides-Extra: travis
Requires-Dist: coveralls; extra == 'travis'
